dual_stepper_motor/stepper_motor_ctrl.vhd
--------------------------------------------------------------------------------
-- Entity   : stepper_motor_ctrl
-- Purpose  : Single-channel stepper motor controller driven entirely by an FSM.
--            Generates the 8-step half-step excitation sequence for a
--            4-wire unipolar stepper motor (IN1..IN4).
--
-- Generics :
--   CLK_FREQ_HZ  – board clock frequency in Hz  (edit at top-level only)
--   STEP_FREQ_HZ – desired stepping rate in Hz   (default 100 steps/s)
--
-- Ports :
--   clk      – system clock (rising-edge)
--   rst      – synchronous active-high reset
--   enable   – '1' = motor runs, '0' = all coils off (free-wheel)
--   dir      – '1' = forward (CW), '0' = backward (CCW)
--   coils    – 4-bit coil drive vector (IN1 downto IN4)
--------------------------------------------------------------------------------

library ieee;
use ieee.std_logic_1164.all;
use ieee.numeric_std.all;

entity stepper_motor_ctrl is
    generic (
        CLK_FREQ_HZ  : positive := 100_000_000;   -- overridden by top-level
        STEP_FREQ_HZ : positive := 100             -- steps per second
    );
    port (
        clk    : in  std_logic;
        rst    : in  std_logic;
        enable : in  std_logic;
        dir    : in  std_logic;
        coils  : out std_logic_vector(3 downto 0)  -- (IN1, IN2, IN3, IN4)
    );
end entity stepper_motor_ctrl;

architecture rtl of stepper_motor_ctrl is

    ---------------------------------------------------------------------------
    -- Timing constant (elaboration-time division, zero hardware cost)
    ---------------------------------------------------------------------------
    constant CYCLES_PER_STEP : positive := CLK_FREQ_HZ / STEP_FREQ_HZ;

    ---------------------------------------------------------------------------
    -- FSM state type  (IDLE + 8 half-step states)
    ---------------------------------------------------------------------------
    type fsm_state_t is (
        IDLE,
        STEP0, STEP1, STEP2, STEP3,
        STEP4, STEP5, STEP6, STEP7
    );

    ---------------------------------------------------------------------------
    -- Internal signals — each driven by exactly ONE process
    ---------------------------------------------------------------------------
    signal state      : fsm_state_t := IDLE;          -- driven by p_fsm only
    signal tick_cnt   : integer range 0 to CYCLES_PER_STEP - 1 := 0;
    signal tick_pulse : std_logic := '0';              -- driven by p_tick only

begin

    ---------------------------------------------------------------------------
    -- Process 1 – Tick generator (registered)
    -- Produces a single-cycle '1' pulse every CYCLES_PER_STEP clock edges.
    ---------------------------------------------------------------------------
    p_tick : process (clk)
    begin
        if rising_edge(clk) then
            if rst = '1' or enable = '0' then
                tick_cnt   <= 0;
                tick_pulse <= '0';
            else
                if tick_cnt = CYCLES_PER_STEP - 1 then
                    tick_cnt   <= 0;
                    tick_pulse <= '1';
                else
                    tick_cnt   <= tick_cnt + 1;
                    tick_pulse <= '0';
                end if;
            end if;
        end if;
    end process p_tick;

    ---------------------------------------------------------------------------
    -- Process 2 – FSM next-state logic (registered)
    -- `state` is the ONLY signal written here.
    ---------------------------------------------------------------------------
    p_fsm : process (clk)
    begin
        if rising_edge(clk) then
            if rst = '1' then
                state <= IDLE;
            else
                case state is

                    when IDLE =>
                        if enable = '1' then
                            state <= STEP0;
                        end if;

                    when STEP0 =>
                        if enable = '0' then
                            state <= IDLE;
                        elsif tick_pulse = '1' then
                            if dir = '1' then state <= STEP1;
                            else              state <= STEP7; end if;
                        end if;

                    when STEP1 =>
                        if enable = '0' then
                            state <= IDLE;
                        elsif tick_pulse = '1' then
                            if dir = '1' then state <= STEP2;
                            else              state <= STEP0; end if;
                        end if;

                    when STEP2 =>
                        if enable = '0' then
                            state <= IDLE;
                        elsif tick_pulse = '1' then
                            if dir = '1' then state <= STEP3;
                            else              state <= STEP1; end if;
                        end if;

                    when STEP3 =>
                        if enable = '0' then
                            state <= IDLE;
                        elsif tick_pulse = '1' then
                            if dir = '1' then state <= STEP4;
                            else              state <= STEP2; end if;
                        end if;

                    when STEP4 =>
                        if enable = '0' then
                            state <= IDLE;
                        elsif tick_pulse = '1' then
                            if dir = '1' then state <= STEP5;
                            else              state <= STEP3; end if;
                        end if;

                    when STEP5 =>
                        if enable = '0' then
                            state <= IDLE;
                        elsif tick_pulse = '1' then
                            if dir = '1' then state <= STEP6;
                            else              state <= STEP4; end if;
                        end if;

                    when STEP6 =>
                        if enable = '0' then
                            state <= IDLE;
                        elsif tick_pulse = '1' then
                            if dir = '1' then state <= STEP7;
                            else              state <= STEP5; end if;
                        end if;

                    when STEP7 =>
                        if enable = '0' then
                            state <= IDLE;
                        elsif tick_pulse = '1' then
                            if dir = '1' then state <= STEP0;
                            else              state <= STEP6; end if;
                        end if;

                    when others =>
                        state <= IDLE;

                end case;
            end if;
        end if;
    end process p_fsm;

    ---------------------------------------------------------------------------
    -- Process 3 – Moore output decoder (purely combinational)
    -- Maps state -> coil pattern directly. No shared signals with other processes.
    -- Half-step table: (IN1, IN2, IN3, IN4)
    ---------------------------------------------------------------------------
    p_output : process (state)
    begin
        case state is
            when STEP0  => coils <= "1000";
            when STEP1  => coils <= "1100";
            when STEP2  => coils <= "0100";
            when STEP3  => coils <= "0110";
            when STEP4  => coils <= "0010";
            when STEP5  => coils <= "0011";
            when STEP6  => coils <= "0001";
            when STEP7  => coils <= "1001";
            when others => coils <= "0000";  -- IDLE: de-energise all coils
        end case;
    end process p_output;

end architecture rtl;

dual_stepper_motor/dual_stepper_top.vhd
--------------------------------------------------------------------------------
-- Entity   : dual_stepper_top
-- Purpose  : Top-level wrapper for two independent stepper motor controllers.
--            Motor 1 → Pmod JA[1..4] (IN1..IN4)
--            Motor 2 → Pmod JB[1..4] (IN1..IN4)
--
-- *** EDIT CLK_FREQ_HZ HERE TO MATCH YOUR BOARD CLOCK ***
--     Basys3 default: 100 MHz
--
-- Controls (tied to slide switches on Basys3):
--   sw(0)  – Motor 1 enable
--   sw(1)  – Motor 1 direction
--   sw(2)  – Motor 2 enable
--   sw(3)  – Motor 2 direction
--   btnC   – Synchronous reset (centre button)
--------------------------------------------------------------------------------

library ieee;
use ieee.std_logic_1164.all;

entity dual_stepper_top is
    generic (
        -- ┌─────────────────────────────────────────────────┐
        -- │  SINGLE POINT OF TRUTH – change only this value │
        -- └─────────────────────────────────────────────────┘
        CLK_FREQ_HZ  : positive := 100_000_000;   -- Basys3: 100 MHz
        STEP_FREQ_HZ : positive := 100             -- 100 steps/s per motor
    );
    port (
        clk   : in  std_logic;                     -- 100 MHz on-board oscillator
        btnC  : in  std_logic;                     -- centre push-button → reset
        sw    : in  std_logic_vector(3 downto 0);  -- slide switches

        -- Pmod JA – Motor 1 (upper row, pins 1-4)
        JA    : out std_logic_vector(3 downto 0);  -- JA(0)=IN1 … JA(3)=IN4

        -- Pmod JB – Motor 2 (upper row, pins 1-4)
        JB    : out std_logic_vector(3 downto 0)   -- JB(0)=IN1 … JB(3)=IN4
    );
end entity dual_stepper_top;

architecture structural of dual_stepper_top is

    ---------------------------------------------------------------------------
    -- Component declaration (matches stepper_motor_ctrl.vhd)
    ---------------------------------------------------------------------------
    component stepper_motor_ctrl is
        generic (
            CLK_FREQ_HZ  : positive;
            STEP_FREQ_HZ : positive
        );
        port (
            clk    : in  std_logic;
            rst    : in  std_logic;
            enable : in  std_logic;
            dir    : in  std_logic;
            coils  : out std_logic_vector(3 downto 0)
        );
    end component stepper_motor_ctrl;

begin

    ---------------------------------------------------------------------------
    -- Instance 1: Motor connected to Pmod JA
    --   sw(0) → enable,  sw(1) → direction
    ---------------------------------------------------------------------------
    U_MOTOR1 : stepper_motor_ctrl
        generic map (
            CLK_FREQ_HZ  => CLK_FREQ_HZ,
            STEP_FREQ_HZ => STEP_FREQ_HZ
        )
        port map (
            clk    => clk,
            rst    => btnC,
            enable => sw(0),
            dir    => sw(1),
            coils  => JA
        );

    ---------------------------------------------------------------------------
    -- Instance 2: Motor connected to Pmod JB
    --   sw(2) → enable,  sw(3) → direction
    ---------------------------------------------------------------------------
    U_MOTOR2 : stepper_motor_ctrl
        generic map (
            CLK_FREQ_HZ  => CLK_FREQ_HZ,
            STEP_FREQ_HZ => STEP_FREQ_HZ
        )
        port map (
            clk    => clk,
            rst    => btnC,
            enable => sw(2),
            dir    => sw(3),
            coils  => JB
        );

end architecture structural;

dual_stepper_motor/tb_dual_stepper.vhd
--------------------------------------------------------------------------------
-- Entity   : tb_dual_stepper
-- Author   : (inspired by Prof. Philippe Velha's style)
-- Purpose  : Self-checking testbench for dual_stepper_top.
--
-- Strategy :
--   • Simulated clock uses a SCALED-DOWN CLK_FREQ_HZ (1 000 Hz) and a
--     STEP_FREQ_HZ of 10 steps/s so the simulation remains fast yet
--     exercises the exact same FSM paths as in silicon.
--   • Five independent test scenarios run sequentially:
--       TC1 – Reset behaviour (all coils = 0)
--       TC2 – Motor 1 forward only
--       TC3 – Motor 2 forward only (Motor 1 idle) → independence check
--       TC4 – Both motors forward simultaneously
--       TC5 – Direction reversal mid-run
--   • Assertion library (assert/report) flags any unexpected coil output.
--   • A final PASS/FAIL banner is printed at the end.
--------------------------------------------------------------------------------

library ieee;
use ieee.std_logic_1164.all;
use ieee.numeric_std.all;

entity tb_dual_stepper is
    -- Testbench has no ports (IEEE 1076 standard practice)
end entity tb_dual_stepper;

architecture sim of tb_dual_stepper is

    ---------------------------------------------------------------------------
    -- Simulation parameters (scaled down for fast simulation)
    ---------------------------------------------------------------------------
    constant SIM_CLK_FREQ_HZ  : positive := 1_000;   -- 1 kHz simulated clock
    constant SIM_STEP_FREQ_HZ : positive := 10;       -- 10 steps/s

    -- Derived timing constants
    constant CLK_PERIOD   : time := 1 sec / SIM_CLK_FREQ_HZ;   -- 1 ms
    constant STEP_PERIOD  : time := 1 sec / SIM_STEP_FREQ_HZ;  -- 100 ms per step
    constant CYCLES_STEP  : positive := SIM_CLK_FREQ_HZ / SIM_STEP_FREQ_HZ; -- 100 cycles

    ---------------------------------------------------------------------------
    -- DUT interface signals
    ---------------------------------------------------------------------------
    signal clk  : std_logic := '0';
    signal btnC : std_logic := '0';
    signal sw   : std_logic_vector(3 downto 0) := (others => '0');
    signal JA   : std_logic_vector(3 downto 0);
    signal JB   : std_logic_vector(3 downto 0);

    ---------------------------------------------------------------------------
    -- Test infrastructure
    ---------------------------------------------------------------------------
    signal test_done   : std_logic := '0';
    signal fail_count  : integer   := 0;

    ---------------------------------------------------------------------------
    -- Half-step reference table (mirrors RTL constant exactly)
    ---------------------------------------------------------------------------
    type coil_table_t is array (0 to 7) of std_logic_vector(3 downto 0);
    constant HALF_STEP_TABLE : coil_table_t := (
        "1000", "1100", "0100", "0110",
        "0010", "0011", "0001", "1001"
    );

    ---------------------------------------------------------------------------
    -- Helper: std_logic_vector → string  (replaces VHDL-2008 to_string,
    --         compatible with VHDL-93 / 2002 / 2008)
    ---------------------------------------------------------------------------
    function slv_to_str (slv : std_logic_vector) return string is
        variable result : string(1 to slv'length);
        variable idx    : integer := 1;
    begin
        for i in slv'range loop
            case slv(i) is
                when '0'    => result(idx) := '0';
                when '1'    => result(idx) := '1';
                when 'U'    => result(idx) := 'U';
                when 'X'    => result(idx) := 'X';
                when 'Z'    => result(idx) := 'Z';
                when '-'    => result(idx) := '-';
                when others => result(idx) := '?';
            end case;
            idx := idx + 1;
        end loop;
        return result;
    end function slv_to_str;

    ---------------------------------------------------------------------------
    -- Helper: wait for N complete steps on a given coil signal.
    -- Samples the coil output once per step period and checks the sequence.
    ---------------------------------------------------------------------------
    procedure wait_and_check_steps (
        signal   coil_sig  : in  std_logic_vector(3 downto 0);
        constant n_steps   : in  positive;
        constant start_idx : in  integer;
        constant forward   : in  boolean;
        variable err_count : inout integer
    ) is
        variable idx  : integer := start_idx;
        variable incr : integer;
    begin
        if forward then incr := 1; else incr := -1; end if;

        for i in 1 to n_steps loop
            -- Wait one full step period (the FSM will have advanced)
            wait for STEP_PERIOD;
            -- Allow one extra clock for registered outputs to settle
            wait for CLK_PERIOD;

            idx := (idx + incr + 8) mod 8;

            if coil_sig /= HALF_STEP_TABLE(idx) then
                report "COIL MISMATCH at step " & integer'image(i)
                     & " expected=" & slv_to_str(HALF_STEP_TABLE(idx))
                     & " got="      & slv_to_str(coil_sig)
                severity warning;
                err_count := err_count + 1;
            end if;
        end loop;
    end procedure wait_and_check_steps;

begin

    ---------------------------------------------------------------------------
    -- DUT instantiation (uses scaled-down generics)
    ---------------------------------------------------------------------------
    DUT : entity work.dual_stepper_top
        generic map (
            CLK_FREQ_HZ  => SIM_CLK_FREQ_HZ,
            STEP_FREQ_HZ => SIM_STEP_FREQ_HZ
        )
        port map (
            clk  => clk,
            btnC => btnC,
            sw   => sw,
            JA   => JA,
            JB   => JB
        );

    ---------------------------------------------------------------------------
    -- Clock generator – free-running, stops when test_done = '1'
    ---------------------------------------------------------------------------
    p_clk : process
    begin
        while test_done = '0' loop
            clk <= '0'; wait for CLK_PERIOD / 2;
            clk <= '1'; wait for CLK_PERIOD / 2;
        end loop;
        wait;
    end process p_clk;

    ---------------------------------------------------------------------------
    -- Stimulus process
    ---------------------------------------------------------------------------
    p_stim : process
        variable errors : integer := 0;
    begin

        -----------------------------------------------------------------------
        -- TC1 – Reset: assert btnC, all coils must be 0
        -----------------------------------------------------------------------
        report "=== TC1: Reset check ===";
        btnC <= '1';
        sw   <= "1111";   -- everything enabled, but reset dominates
        wait for 5 * CLK_PERIOD;

        assert JA = "0000"
            report "TC1 FAIL: JA not 0 during reset" severity warning;
        if JA /= "0000" then errors := errors + 1; end if;

        assert JB = "0000"
            report "TC1 FAIL: JB not 0 during reset" severity warning;
        if JB /= "0000" then errors := errors + 1; end if;

        -- Release reset
        btnC <= '0';
        sw   <= "0000";
        wait for 5 * CLK_PERIOD;

        -----------------------------------------------------------------------
        -- TC2 – Motor 1 forward only (sw(0)='1', sw(1)='1')
        --       Motor 2 disabled → JB must stay "0000"
        -----------------------------------------------------------------------
        report "=== TC2: Motor 1 forward, Motor 2 idle ===";
        sw <= "0011";  -- enable M1, dir M1 = forward; M2 off
        wait for 5 * CLK_PERIOD;   -- let FSM enter STEP0

        -- Check that M2 coils stay zero
        wait for 3 * STEP_PERIOD;
        assert JB = "0000"
            report "TC2 FAIL: JB should be 0 when Motor 2 is disabled" severity warning;
        if JB /= "0000" then errors := errors + 1; end if;

        -- Stop Motor 1
        sw <= "0000";
        wait for 2 * CLK_PERIOD;
        assert JA = "0000"
            report "TC2 FAIL: JA should de-energise when disabled" severity warning;
        if JA /= "0000" then errors := errors + 1; end if;

        -----------------------------------------------------------------------
        -- TC3 – Motor 2 forward only (independence check)
        -----------------------------------------------------------------------
        report "=== TC3: Motor 2 forward, Motor 1 idle ===";
        sw <= "1100";  -- enable M2, dir M2 = forward; M1 off
        wait for 5 * CLK_PERIOD;

        wait for 3 * STEP_PERIOD;
        assert JA = "0000"
            report "TC3 FAIL: JA should be 0 when Motor 1 is disabled" severity warning;
        if JA /= "0000" then errors := errors + 1; end if;

        sw <= "0000";
        wait for 2 * CLK_PERIOD;

        -----------------------------------------------------------------------
        -- TC4 – Both motors running forward simultaneously
        -----------------------------------------------------------------------
        report "=== TC4: Both motors forward ===";

        -- Full reset before synchronised start
        btnC <= '1';
        wait for 3 * CLK_PERIOD;
        btnC <= '0';
        wait for 3 * CLK_PERIOD;

        sw <= "1111";   -- M1 enable + forward, M2 enable + forward
        wait for 5 * CLK_PERIOD;

        -- Allow 8 full steps (one complete electrical cycle)
        wait for 8 * STEP_PERIOD + CLK_PERIOD;

        -- After one full cycle the coil pattern must be back at HALF_STEP_TABLE(0)
        -- (both motors started from STEP0 after reset)
        assert JA = HALF_STEP_TABLE(0)
            report "TC4 FAIL: JA not at step-0 after 8 steps" severity warning;
        if JA /= HALF_STEP_TABLE(0) then errors := errors + 1; end if;

        assert JB = HALF_STEP_TABLE(0)
            report "TC4 FAIL: JB not at step-0 after 8 steps" severity warning;
        if JB /= HALF_STEP_TABLE(0) then errors := errors + 1; end if;

        sw <= "0000";
        wait for 2 * CLK_PERIOD;

        -----------------------------------------------------------------------
        -- TC5 – Direction reversal mid-run on Motor 1
        -----------------------------------------------------------------------
        report "=== TC5: Direction reversal ===";

        btnC <= '1'; wait for 3 * CLK_PERIOD;
        btnC <= '0'; wait for 3 * CLK_PERIOD;

        -- Start Motor 1 forward for 4 steps
        sw <= "0011";
        wait for 4 * STEP_PERIOD + CLK_PERIOD;

        -- Reverse direction (keep enable, flip dir)
        sw <= "0001";
        wait for 4 * STEP_PERIOD + CLK_PERIOD;

        -- After 4 forward + 4 backward the motor should be back near step 0
        -- (not bit-exact due to reversal latency, just check no lockup)
        assert JA /= "XXXX"
            report "TC5 FAIL: JA driven to unknowns after reversal" severity warning;

        sw <= "0000";

        -----------------------------------------------------------------------
        -- End of test
        -----------------------------------------------------------------------
        wait for 5 * CLK_PERIOD;

      
    end process p_stim;

end architecture sim;

dual_stepper_motor/sim.vcd
$date
  Wed Mar 25 21:48:08 2026
$end
$version
  GHDL v0
$end
$timescale
  1 fs
$end
$scope module standard $end
$upscope $end
$scope module std_logic_1164 $end
$upscope $end
$scope module numeric_std $end
$upscope $end
$scope module tb_dual_stepper $end
$var reg 1 ! clk $end
$var reg 1 " btnc $end
$var reg 4 # sw[3:0] $end
$var reg 4 $ ja[3:0] $end
$var reg 4 % jb[3:0] $end
$var reg 1 & test_done $end
$var integer 32 ' fail_count $end
$scope module dut $end
$var reg 1 ( clk $end
$var reg 1 ) btnc $end
$var reg 4 * sw[3:0] $end
$var reg 4 + ja[3:0] $end
$var reg 4 , jb[3:0] $end
$scope module u_motor1 $end
$var reg 1 - clk $end
$var reg 1 . rst $end
$var reg 1 / enable $end
$var reg 1 0 dir $end
$var reg 4 1 coils[3:0] $end
$comment state is not handled $end
$var integer 32 2 tick_cnt $end
$var reg 1 3 tick_pulse $end
$upscope $end
$scope module u_motor2 $end
$var reg 1 4 clk $end
$var reg 1 5 rst $end
$var reg 1 6 enable $end
$var reg 1 7 dir $end
$var reg 4 8 coils[3:0] $end
$comment state is not handled $end
$var integer 32 9 tick_cnt $end
$var reg 1 : tick_pulse $end
$upscope $end
$upscope $end
$upscope $end
$enddefinitions $end
#0
0!
1"
b1111 #
b0000 $
b0000 %
0&
b0 '
0(
1)
b1111 *
b0000 +
b0000 ,
0-
1.
1/
10
b0000 1
b0 2
03
04
15
16
17
b0000 8
b0 9
0:
#500000000000
1!
1(
1-
14
#1000000000000
0!
0(
0-
04
#1500000000000
1!
1(
1-
14
#2000000000000
0!
0(
0-
04
#2500000000000
1!
1(
1-
14
#3000000000000
0!
0(
0-
04
#3500000000000
1!
1(
1-
14
#4000000000000
0!
0(
0-
04
#4500000000000
1!
1(
1-
14
#5000000000000
0!
0"
b0000 #
0(
0)
b0000 *
0-
0.
0/
00
04
05
06
07
#5500000000000
1!
1(
1-
14
#6000000000000
0!
0(
0-
04
#6500000000000
1!
1(
1-
14
#7000000000000
0!
0(
0-
04
#7500000000000
1!
1(
1-
14
#8000000000000
0!
0(
0-
04
#8500000000000
1!
1(
1-
14
#9000000000000
0!
0(
0-
04
#9500000000000
1!
1(
1-
14
#10000000000000
0!
b0011 #
0(
b0011 *
0-
1/
10
04
#10500000000000
1!
b1000 $
1(
b1000 +
1-
b1000 1
b1 2
14
#11000000000000
0!
0(
0-
04
#11500000000000
1!
1(
1-
b10 2
14
#12000000000000
0!
0(
0-
04
#12500000000000
1!
1(
1-
b11 2
14
#13000000000000
0!
0(
0-
04
#13500000000000
1!
1(
1-
b100 2
14
#14000000000000
0!
0(
0-
04
#14500000000000
1!
1(
1-
b101 2
14
#15000000000000
0!
0(
0-
04
#15500000000000
1!
1(
1-
b110 2
14
#16000000000000
0!
0(
0-
04
#16500000000000
1!
1(
1-
b111 2
14
#17000000000000
0!
0(
0-
04
#17500000000000
1!
1(
1-
b1000 2
14
#18000000000000
0!
0(
0-
04
#18500000000000
1!
1(
1-
b1001 2
14
#19000000000000
0!
0(
0-
04
#19500000000000
1!
1(
1-
b1010 2
14
#20000000000000
0!
0(
0-
04
#20500000000000
1!
1(
1-
b1011 2
14
#21000000000000
0!
0(
0-
04
#21500000000000
1!
1(
1-
b1100 2
14
#22000000000000
0!
0(
0-
04
#22500000000000
1!
1(
1-
b1101 2
14
#23000000000000
0!
0(
0-
04
#23500000000000
1!
1(
1-
b1110 2
14
#24000000000000
0!
0(
0-
04
#24500000000000
1!
1(
1-
b1111 2
14
#25000000000000
0!
0(
0-
04
#25500000000000
1!
1(
1-
b10000 2
14
#26000000000000
0!
0(
0-
04
#26500000000000
1!
1(
1-
b10001 2
14
#27000000000000
0!
0(
0-
04
#27500000000000
1!
1(
1-
b10010 2
14
#28000000000000
0!
0(
0-
04
#28500000000000
1!
1(
1-
b10011 2
14
#29000000000000
0!
0(
0-
04
#29500000000000
1!
1(
1-
b10100 2
14
#30000000000000
0!
0(
0-
04
#30500000000000
1!
1(
1-
b10101 2
14
#31000000000000
0!
0(
0-
04
#31500000000000
1!
1(
1-
b10110 2
14
#32000000000000
0!
0(
0-
04
#32500000000000
1!
1(
1-
b10111 2
14
#33000000000000
0!
0(
0-
04
#33500000000000
1!
1(
1-
b11000 2
14
#34000000000000
0!
0(
0-
04
#34500000000000
1!
1(
1-
b11001 2
14
#35000000000000
0!
0(
0-
04
#35500000000000
1!
1(
1-
b11010 2
14
#36000000000000
0!
0(
0-
04
#36500000000000
1!
1(
1-
b11011 2
14
#37000000000000
0!
0(
0-
04
#37500000000000
1!
1(
1-
b11100 2
14
#38000000000000
0!
0(
0-
04
#38500000000000
1!
1(
1-
b11101 2
14
#39000000000000
0!
0(
0-
04
#39500000000000
1!
1(
1-
b11110 2
14
#40000000000000
0!
0(
0-
04
#40500000000000
1!
1(
1-
b11111 2
14
#41000000000000
0!
0(
0-
04
#41500000000000
1!
1(
1-
b100000 2
14
#42000000000000
0!
0(
0-
04
#42500000000000
1!
1(
1-
b100001 2
14
#43000000000000
0!
0(
0-
04
#43500000000000
1!
1(
1-
b100010 2
14
#44000000000000
0!
0(
0-
04
#44500000000000
1!
1(
1-
b100011 2
14
#45000000000000
0!
0(
0-
04
#45500000000000
1!
1(
1-
b100100 2
14
#46000000000000
0!
0(
0-
04
#46500000000000
1!
1(
1-
b100101 2
14
#47000000000000
0!
0(
0-
04
#47500000000000
1!
1(
1-
b100110 2
14
#48000000000000
0!
0(
0-
04
#48500000000000
1!
1(
1-
b100111 2
14
#49000000000000
0!
0(
0-
04
#49500000000000
1!
1(
1-
b101000 2
14
#50000000000000
0!
0(
0-
04
#50500000000000
1!
1(
1-
b101001 2
14
#51000000000000
0!
0(
0-
04
#51500000000000
1!
1(
1-
b101010 2
14
#52000000000000
0!
0(
0-
04
#52500000000000
1!
1(
1-
b101011 2
14
#53000000000000
0!
0(
0-
04
#53500000000000
1!
1(
1-
b101100 2
14
#54000000000000
0!
0(
0-
04
#54500000000000
1!
1(
1-
b101101 2
14
#55000000000000
0!
0(
0-
04
#55500000000000
1!
1(
1-
b101110 2
14
#56000000000000
0!
0(
0-
04
#56500000000000
1!
1(
1-
b101111 2
14
#57000000000000
0!
0(
0-
04
#57500000000000
1!
1(
1-
b110000 2
14
#58000000000000
0!
0(
0-
04
#58500000000000
1!
1(
1-
b110001 2
14
#59000000000000
0!
0(
0-
04
#59500000000000
1!
1(
1-
b110010 2
14
#60000000000000
0!
0(
0-
04
#60500000000000
1!
1(
1-
b110011 2
14
#61000000000000
0!
0(
0-
04
#61500000000000
1!
1(
1-
b110100 2
14
#62000000000000
0!
0(
0-
04
#62500000000000
1!
1(
1-
b110101 2
14
#63000000000000
0!
0(
0-
04
#63500000000000
1!
1(
1-
b110110 2
14
#64000000000000
0!
0(
0-
04
#64500000000000
1!
1(
1-
b110111 2
14
#65000000000000
0!
0(
0-
04
#65500000000000
1!
1(
1-
b111000 2
14
#66000000000000
0!
0(
0-
04
#66500000000000
1!
1(
1-
b111001 2
14
#67000000000000
0!
0(
0-
04
#67500000000000
1!
1(
1-
b111010 2
14
#68000000000000
0!
0(
0-
04
#68500000000000
1!
1(
1-
b111011 2
14
#69000000000000
0!
0(
0-
04
#69500000000000
1!
1(
1-
b111100 2
14
#70000000000000
0!
0(
0-
04
#70500000000000
1!
1(
1-
b111101 2
14
#71000000000000
0!
0(
0-
04
#71500000000000
1!
1(
1-
b111110 2
14
#72000000000000
0!
0(
0-
04
#72500000000000
1!
1(
1-
b111111 2
14
#73000000000000
0!
0(
0-
04
#73500000000000
1!
1(
1-
b1000000 2
14
#74000000000000
0!
0(
0-
04
#74500000000000
1!
1(
1-
b1000001 2
14
#75000000000000
0!
0(
0-
04
#75500000000000
1!
1(
1-
b1000010 2
14
#76000000000000
0!
0(
0-
04
#76500000000000
1!
1(
1-
b1000011 2
14
#77000000000000
0!
0(
0-
04
#77500000000000
1!
1(
1-
b1000100 2
14
#78000000000000
0!
0(
0-
04
#78500000000000
1!
1(
1-
b1000101 2
14
#79000000000000
0!
0(
0-
04
#79500000000000
1!
1(
1-
b1000110 2
14
#80000000000000
0!
0(
0-
04
#80500000000000
1!
1(
1-
b1000111 2
14
#81000000000000
0!
0(
0-
04
#81500000000000
1!
1(
1-
b1001000 2
14
#82000000000000
0!
0(
0-
04
#82500000000000
1!
1(
1-
b1001001 2
14
#83000000000000
0!
0(
0-
04
#83500000000000
1!
1(
1-
b1001010 2
14
#84000000000000
0!
0(
0-
04
#84500000000000
1!
1(
1-
b1001011 2
14
#85000000000000
0!
0(
0-
04
#85500000000000
1!
1(
1-
b1001100 2
14
#86000000000000
0!
0(
0-
04
#86500000000000
1!
1(
1-
b1001101 2
14
#87000000000000
0!
0(
0-
04
#87500000000000
1!
1(
1-
b1001110 2
14
#88000000000000
0!
0(
0-
04
#88500000000000
1!
1(
1-
b1001111 2
14
#89000000000000
0!
0(
0-
04
#89500000000000
1!
1(
1-
b1010000 2
14
#90000000000000
0!
0(
0-
04
#90500000000000
1!
1(
1-
b1010001 2
14
#91000000000000
0!
0(
0-
04
#91500000000000
1!
1(
1-
b1010010 2
14
#92000000000000
0!
0(
0-
04
#92500000000000
1!
1(
1-
b1010011 2
14
#93000000000000
0!
0(
0-
04
#93500000000000
1!
1(
1-
b1010100 2
14
#94000000000000
0!
0(
0-
04
#94500000000000
1!
1(
1-
b1010101 2
14
#95000000000000
0!
0(
0-
04
#95500000000000
1!
1(
1-
b1010110 2
14
#96000000000000
0!
0(
0-
04
#96500000000000
1!
1(
1-
b1010111 2
14
#97000000000000
0!
0(
0-
04
#97500000000000
1!
1(
1-
b1011000 2
14
#98000000000000
0!
0(
0-
04
#98500000000000
1!
1(
1-
b1011001 2
14
#99000000000000
0!
0(
0-
04
#99500000000000
1!
1(
1-
b1011010 2
14
#100000000000000
0!
0(
0-
04
#100500000000000
1!
1(
1-
b1011011 2
14
#101000000000000
0!
0(
0-
04
#101500000000000
1!
1(
1-
b1011100 2
14
#102000000000000
0!
0(
0-
04
#102500000000000
1!
1(
1-
b1011101 2
14
#103000000000000
0!
0(
0-
04
#103500000000000
1!
1(
1-
b1011110 2
14
#104000000000000
0!
0(
0-
04
#104500000000000
1!
1(
1-
b1011111 2
14
#105000000000000
0!
0(
0-
04
#105500000000000
1!
1(
1-
b1100000 2
14
#106000000000000
0!
0(
0-
04
#106500000000000
1!
1(
1-
b1100001 2
14
#107000000000000
0!
0(
0-
04
#107500000000000
1!
1(
1-
b1100010 2
14
#108000000000000
0!
0(
0-
04
#108500000000000
1!
1(
1-
b1100011 2
14
#109000000000000
0!
0(
0-
04
#109500000000000
1!
1(
1-
b0 2
13
14
#110000000000000
0!
0(
0-
04
#110500000000000
1!
b1100 $
1(
b1100 +
1-
b1100 1
b1 2
03
14
#111000000000000
0!
0(
0-
04
#111500000000000
1!
1(
1-
b10 2
14
#112000000000000
0!
0(
0-
04
#112500000000000
1!
1(
1-
b11 2
14
#113000000000000
0!
0(
0-
04
#113500000000000
1!
1(
1-
b100 2
14
#114000000000000
0!
0(
0-
04
#114500000000000
1!
1(
1-
b101 2
14
#115000000000000
0!
0(
0-
04
#115500000000000
1!
1(
1-
b110 2
14
#116000000000000
0!
0(
0-
04
#116500000000000
1!
1(
1-
b111 2
14
#117000000000000
0!
0(
0-
04
#117500000000000
1!
1(
1-
b1000 2
14
#118000000000000
0!
0(
0-
04
#118500000000000
1!
1(
1-
b1001 2
14
#119000000000000
0!
0(
0-
04
#119500000000000
1!
1(
1-
b1010 2
14
#120000000000000
0!
0(
0-
04
#120500000000000
1!
1(
1-
b1011 2
14
#121000000000000
0!
0(
0-
04
#121500000000000
1!
1(
1-
b1100 2
14
#122000000000000
0!
0(
0-
04
#122500000000000
1!
1(
1-
b1101 2
14
#123000000000000
0!
0(
0-
04
#123500000000000
1!
1(
1-
b1110 2
14
#124000000000000
0!
0(
0-
04
#124500000000000
1!
1(
1-
b1111 2
14
#125000000000000
0!
0(
0-
04
#125500000000000
1!
1(
1-
b10000 2
14
#126000000000000
0!
0(
0-
04
#126500000000000
1!
1(
1-
b10001 2
14
#127000000000000
0!
0(
0-
04
#127500000000000
1!
1(
1-
b10010 2
14
#128000000000000
0!
0(
0-
04
#128500000000000
1!
1(
1-
b10011 2
14
#129000000000000
0!
0(
0-
04
#129500000000000
1!
1(
1-
b10100 2
14
#130000000000000
0!
0(
0-
04
#130500000000000
1!
1(
1-
b10101 2
14
#131000000000000
0!
0(
0-
04
#131500000000000
1!
1(
1-
b10110 2
14
#132000000000000
0!
0(
0-
04
#132500000000000
1!
1(
1-
b10111 2
14
#133000000000000
0!
0(
0-
04
#133500000000000
1!
1(
1-
b11000 2
14
#134000000000000
0!
0(
0-
04
#134500000000000
1!
1(
1-
b11001 2
14
#135000000000000
0!
0(
0-
04
#135500000000000
1!
1(
1-
b11010 2
14
#136000000000000
0!
0(
0-
04
#136500000000000
1!
1(
1-
b11011 2
14
#137000000000000
0!
0(
0-
04
#137500000000000
1!
1(
1-
b11100 2
14
#138000000000000
0!
0(
0-
04
#138500000000000
1!
1(
1-
b11101 2
14
#139000000000000
0!
0(
0-
04
